[
    {
        "key": "dbln",
        "value": "%7B%22100074168221343%22%3A%221bhGdcYE%22%2C%22100095161689728%22%3A%22r04HWG4E%22%2C%2261565354446986%22%3A%22JMmSO7Nf%22%2C%22100081185143782%22%3A%22eTgSFSGj%22%7D",
        "domain": "facebook.com",
        "path": "/login/device-based/",
        "hostOnly": false,
        "creation": "2024-10-01T14:43:13.986Z",
        "lastAccessed": "2024-10-01T14:43:13.987Z"
    },
    {
        "key": "datr",
        "value": "DIPdZvHy_wvyISE4kfUN0upF",
        "domain": "facebook.com",
        "path": "/",
        "hostOnly": false,
        "creation": "2024-10-01T14:43:13.987Z",
        "lastAccessed": "2024-10-01T14:43:13.987Z"
    },
    {
        "key": "sb",
        "value": "DIPdZopcH_bSMirjCHhL-Gco",
        "domain": "facebook.com",
        "path": "/",
        "hostOnly": false,
        "creation": "2024-10-01T14:43:13.987Z",
        "lastAccessed": "2024-10-01T14:43:13.987Z"
    },
    {
        "key": "ps_l",
        "value": "1",
        "domain": "facebook.com",
        "path": "/",
        "hostOnly": false,
        "creation": "2024-10-01T14:43:13.987Z",
        "lastAccessed": "2024-10-01T14:43:13.987Z"
    },
    {
        "key": "ps_n",
        "value": "1",
        "domain": "facebook.com",
        "path": "/",
        "hostOnly": false,
        "creation": "2024-10-01T14:43:13.987Z",
        "lastAccessed": "2024-10-01T14:43:13.987Z"
    },
    {
        "key": "vpd",
        "value": "v1%3B688x360x2",
        "domain": "facebook.com",
        "path": "/",
        "hostOnly": false,
        "creation": "2024-10-01T14:43:13.987Z",
        "lastAccessed": "2024-10-01T14:43:13.987Z"
    },
    {
        "key": "locale",
        "value": "en_US",
        "domain": "facebook.com",
        "path": "/",
        "hostOnly": false,
        "creation": "2024-10-01T14:43:13.987Z",
        "lastAccessed": "2024-10-01T14:43:13.987Z"
    },
    {
        "key": "wd",
        "value": "360x688",
        "domain": "facebook.com",
        "path": "/",
        "hostOnly": false,
        "creation": "2024-10-01T14:43:13.987Z",
        "lastAccessed": "2024-10-01T14:43:13.987Z"
    },
    {
        "key": "c_user",
        "value": "100081185143782",
        "domain": "facebook.com",
        "path": "/",
        "hostOnly": false,
        "creation": "2024-10-01T14:43:13.987Z",
        "lastAccessed": "2024-10-01T14:43:13.987Z"
    },
    {
        "key": "xs",
        "value": "27%3ARsheshLCnIXnCw%3A2%3A1727792674%3A-1%3A5134",
        "domain": "facebook.com",
        "path": "/",
        "hostOnly": false,
        "creation": "2024-10-01T14:43:13.987Z",
        "lastAccessed": "2024-10-01T14:43:13.987Z"
    },
    {
        "key": "fr",
        "value": "0kYj7GIYJOGaKVnlp.AWW4UW5D7jTpJXxPtd4twWUVuho.Bm3YMM..AAA.0.0.Bm_AYj.AWXwqi_8iIs",
        "domain": "facebook.com",
        "path": "/",
        "hostOnly": false,
        "creation": "2024-10-01T14:43:13.987Z",
        "lastAccessed": "2024-10-01T14:43:13.987Z"
    },
    {
        "key": "fbl_st",
        "value": "101621478%3BT%3A28796563",
        "domain": "facebook.com",
        "path": "/",
        "hostOnly": false,
        "creation": "2024-10-01T14:43:13.987Z",
        "lastAccessed": "2024-10-01T14:43:13.987Z"
    },
    {
        "key": "wl_cbv",
        "value": "v2%3Bclient_version%3A2635%3Btimestamp%3A1727793791",
        "domain": "facebook.com",
        "path": "/",
        "hostOnly": false,
        "creation": "2024-10-01T14:43:13.987Z",
        "lastAccessed": "2024-10-01T14:43:13.987Z"
    }
]
